README.md
setup.py
bio_minos.egg-info/PKG-INFO
bio_minos.egg-info/SOURCES.txt
bio_minos.egg-info/dependency_links.txt
bio_minos.egg-info/requires.txt
bio_minos.egg-info/top_level.txt
minos/__init__.py
minos/adjudicator.py
minos/bam_read_extract.py
minos/dependencies.py
minos/dnadiff.py
minos/dnadiff_mapping_based_verifier.py
minos/evaluate_recall.py
minos/genotype_confidence_simulator.py
minos/genotyper.py
minos/gramtools.py
minos/mapping_based_verifier.py
minos/multi_sample_pipeline.py
minos/plots.py
minos/utils.py
minos/vcf_chunker.py
minos/vcf_file_split_deletions.py
minos/tasks/__init__.py
minos/tasks/adjudicate.py
minos/tasks/check_recall.py
minos/tasks/check_snps.py
minos/tasks/check_with_ref.py
minos/tasks/cluster_vcfs.py
minos/tasks/make_split_gramtools_build.py
minos/tasks/multi_sample_pipeline.py
minos/tasks/versions.py
scripts/minos