Metadata-Version: 1.1
Name: bio-minos
Version: 0.9.0
Summary: Variant call adjudication
Home-page: https://github.com/iqbal-lab-org/minos
Author: Martin Hunt
Author-email: mhunt@ebi.ac.uk
License: MIT
Platform: UNKNOWN
Classifier: Development Status :: 4 - Beta
Classifier: Topic :: Scientific/Engineering :: Bio-Informatics
Classifier: Programming Language :: Python :: 3 :: Only
Classifier: License :: OSI Approved :: MIT License
